git/__init__.py
pygit_client-0.0.0.dist-info/LICENSE
pygit_client-0.0.0.dist-info/METADATA
pygit_client-0.0.0.dist-info/WHEEL
pygit_client-0.0.0.dist-info/top_level.txt
pygit_client-0.0.0.dist-info/RECORD
