Metadata-Version: 2.1
Name: pygit-client
Version: 0.0.0
Summary: A Python-based Git Client
Author-email: Lance Eftink <leftink@hotmail.com>
License: MIT License        
Project-URL: Homepage, https://github.com/leftink/pygit-client.git
Classifier: License :: OSI Approved :: MIT License
Classifier: Programming Language :: Python :: 3 :: Only
Classifier: Programming Language :: Python :: 3.10
Classifier: Operating System :: OS Independent
Classifier: Typing :: Typed
Requires-Python: >=3.10
License-File: LICENSE
Requires-Dist: requests
